Metadata-Version: 2.1
Name: easynotify
Version: 0.1.1
Home-page: https://github.com/CauchyComplete/EasyNotify
Author: CauchyComplete
Author-email: corundum240@gmail.com
License: MIT
License-File: LICENSE
